{
  "id": 49345051,
  "date": 1758300608,
  "year": 2025,
  "type": 0,
  "context": 2,
  "status": 2,
  "winner": 2,
  "leeks1": [
    {
      "id": 129288,
      "name": "EbolaLeek",
      "level": 216,
      "talent": 780,
      "hat": 0,
      "skin": 24,
      "farmer": 18035,
      "weapon": 0,
      "title": [],
      "metal": 0,
      "face": 0
    }
  ],
  "leeks2": [
    {
      "id": 91393,
      "name": "WeekyLeak",
      "level": 224,
      "talent": 809,
      "hat": 0,
      "skin": 5,
      "farmer": 86213,
      "weapon": 0,
      "title": [],
      "metal": 0,
      "face": 2
    }
  ],
  "farmers1": {
    "18035": {
      "id": 18035,
      "name": "Virus",
      "avatar_changed": 1756478013,
      "muted": false
    }
  },
  "farmers2": {
    "86213": {
      "id": 86213,
      "name": "Rosman",
      "avatar_changed": 1663854939,
      "muted": false
    }
  },
  "report": {
    "bonus": 1,
    "duration": 11,
    "leeks1": [
      {
        "appearance": 8,
        "cur_xp": 5460951,
        "dead": true,
        "id": 129288,
        "level": 216,
        "money": 423,
        "name": "EbolaLeek",
        "next_xp": 5467137,
        "prev_xp": 5389956,
        "resources": {},
        "talent": 785,
        "talent_gain": -15,
        "tb": 132,
        "td": 95,
        "xp": 509,
        "xp_locked": false
      }
    ],
    "leeks2": [
      {
        "appearance": 8,
        "cur_xp": 6104226,
        "dead": false,
        "id": 91393,
        "level": 224,
        "money": 1733,
        "name": "WeekyLeak",
        "next_xp": 6105408,
        "prev_xp": 6023581,
        "resources": {},
        "talent": 779,
        "talent_gain": 15,
        "tb": 110,
        "td": 31,
        "xp": 2276,
        "xp_locked": false
      }
    ],
    "win": 2
  },
  "comments": [],
  "tournament": -1,
  "views": 1,
  "starter": 18035,
  "trophies": [],
  "seed": 1813797462,
  "team1_name": "EbolaLeek",
  "team2_name": "WeekyLeak",
  "data": {
    "actions": [
      [
        0
      ],
      [
        7,
        1
      ],
      [
        13,
        9
      ],
      [
        12,
        43,
        366,
        1
      ],
      [
        9,
        1,
        2,
        366,
        1
      ],
      [
        203,
        "Hi there"
      ],
      [
        203,
        "ready to fight it out?"
      ],
      [
        10,
        1,
        401,
        [
          384,
          401
        ]
      ],
      [
        8,
        1,
        14,
        5
      ],
      [
        7,
        2
      ],
      [
        10,
        2,
        384,
        [
          384
        ]
      ],
      [
        12,
        19,
        401,
        1
      ],
      [
        302,
        21,
        0,
        2,
        1,
        6,
        37,
        2
      ],
      [
        8,
        2,
        6,
        2
      ],
      [
        7,
        0
      ],
      [
        12,
        33,
        143,
        2
      ],
      [
        302,
        15,
        1,
        0,
        0,
        32,
        3,
        3
      ],
      [
        12,
        24,
        143,
        1
      ],
      [
        302,
        8,
        2,
        0,
        0,
        38,
        81,
        2
      ],
      [
        10,
        0,
        161,
        [
          161
        ]
      ],
      [
        10,
        0,
        144,
        [
          144
        ]
      ],
      [
        10,
        0,
        162,
        [
          162
        ]
      ],
      [
        10,
        0,
        180,
        [
          180
        ]
      ],
      [
        10,
        0,
        198,
        [
          198
        ]
      ],
      [
        10,
        0,
        216,
        [
          216
        ]
      ],
      [
        10,
        0,
        234,
        [
          234
        ]
      ],
      [
        13,
        7
      ],
      [
        8,
        0,
        20,
        7
      ],
      [
        6,
        2
      ],
      [
        7,
        1
      ],
      [
        10,
        1,
        416,
        [
          383,
          365,
          382,
          399,
          416
        ]
      ],
      [
        12,
        20,
        416,
        1
      ],
      [
        302,
        22,
        3,
        1,
        1,
        6,
        50,
        4
      ],
      [
        12,
        60,
        416,
        2
      ],
      [
        302,
        96,
        4,
        1,
        1,
        42,
        235,
        3
      ],
      [
        8,
        1,
        14,
        5
      ],
      [
        7,
        2
      ],
      [
        10,
        2,
        418,
        [
          401,
          418
        ]
      ],
      [
        8,
        2,
        6,
        2
      ],
      [
        7,
        0
      ],
      [
        12,
        27,
        234,
        2
      ],
      [
        302,
        9,
        5,
        0,
        0,
        41,
        126,
        2
      ],
      [
        10,
        0,
        217,
        [
          217
        ]
      ],
      [
        10,
        0,
        200,
        [
          200
        ]
      ],
      [
        10,
        0,
        218,
        [
          218
        ]
      ],
      [
        10,
        0,
        236,
        [
          236
        ]
      ],
      [
        10,
        0,
        254,
        [
          254
        ]
      ],
      [
        10,
        0,
        272,
        [
          272
        ]
      ],
      [
        10,
        0,
        255,
        [
          255
        ]
      ],
      [
        8,
        0,
        20,
        7
      ],
      [
        6,
        3
      ],
      [
        7,
        1
      ],
      [
        10,
        1,
        326,
        [
          398,
          380,
          362,
          344,
          326
        ]
      ],
      [
        12,
        18,
        326,
        2
      ],
      [
        302,
        20,
        6,
        1,
        1,
        6,
        113,
        3
      ],
      [
        12,
        24,
        326,
        1
      ],
      [
        302,
        8,
        7,
        1,
        1,
        38,
        82,
        2
      ],
      [
        12,
        34,
        326,
        1
      ],
      [
        302,
        16,
        8,
        1,
        1,
        32,
        5,
        1
      ],
      [
        12,
        33,
        326,
        1
      ],
      [
        302,
        15,
        9,
        1,
        1,
        32,
        2,
        3
      ],
      [
        12,
        16,
        255,
        2
      ],
      [
        101,
        0,
        487,
        73
      ],
      [
        12,
        21,
        326,
        1
      ],
      [
        302,
        23,
        10,
        1,
        1,
        5,
        22,
        2
      ],
      [
        8,
        1,
        21,
        5
      ],
      [
        7,
        2
      ],
      [
        303,
        0
      ],
      [
        10,
        2,
        382,
        [
          400,
          382
        ]
      ],
      [
        8,
        2,
        6,
        2
      ],
      [
        7,
        0
      ],
      [
        303,
        2
      ],
      [
        13,
        23
      ],
      [
        16,
        326,
        1
      ],
      [
        101,
        1,
        106,
        5
      ],
      [
        16,
        326,
        1
      ],
      [
        101,
        1,
        100,
        5
      ],
      [
        16,
        326,
        2
      ],
      [
        101,
        1,
        200,
        30
      ],
      [
        8,
        0,
        20,
        7
      ],
      [
        6,
        4
      ],
      [
        7,
        1
      ],
      [
        303,
        8
      ],
      [
        10,
        1,
        273,
        [
          308,
          291,
          273
        ]
      ],
      [
        13,
        35
      ],
      [
        16,
        255,
        1
      ],
      [
        101,
        0,
        304,
        15
      ],
      [
        103,
        1,
        61
      ],
      [
        301,
        277,
        11,
        1,
        1,
        54,
        8,
        2,
        5
      ],
      [
        16,
        255,
        1
      ],
      [
        101,
        0,
        300,
        15
      ],
      [
        103,
        1,
        60
      ],
      [
        14,
        11,
        8
      ],
      [
        12,
        1,
        273,
        1
      ],
      [
        103,
        1,
        69
      ],
      [
        8,
        1,
        16,
        5
      ],
      [
        7,
        2
      ],
      [
        10,
        2,
        416,
        [
          399,
          416
        ]
      ],
      [
        8,
        2,
        6,
        2
      ],
      [
        7,
        0
      ],
      [
        303,
        1
      ],
      [
        303,
        5
      ],
      [
        12,
        24,
        255,
        2
      ],
      [
        302,
        8,
        12,
        0,
        0,
        38,
        117,
        2
      ],
      [
        10,
        0,
        237,
        [
          237
        ]
      ],
      [
        16,
        273,
        2
      ],
      [
        101,
        1,
        170,
        26
      ],
      [
        16,
        273,
        1
      ],
      [
        101,
        1,
        94,
        5
      ],
      [
        8,
        0,
        17,
        7
      ],
      [
        6,
        5
      ],
      [
        7,
        1
      ],
      [
        303,
        4
      ],
      [
        303,
        7
      ],
      [
        303,
        10
      ],
      [
        10,
        1,
        255,
        [
          255
        ]
      ],
      [
        16,
        237,
        1
      ],
      [
        101,
        0,
        264,
        13
      ],
      [
        103,
        1,
        53
      ],
      [
        301,
        277,
        13,
        1,
        1,
        54,
        8,
        2,
        5
      ],
      [
        16,
        237,
        1
      ],
      [
        101,
        0,
        278,
        14
      ],
      [
        103,
        1,
        56
      ],
      [
        14,
        13,
        8
      ],
      [
        12,
        2,
        255,
        2
      ],
      [
        103,
        1,
        176
      ],
      [
        8,
        1,
        16,
        5
      ],
      [
        7,
        2
      ],
      [
        10,
        2,
        380,
        [
          398,
          380
        ]
      ],
      [
        8,
        2,
        6,
        2
      ],
      [
        7,
        0
      ],
      [
        12,
        4,
        237,
        1
      ],
      [
        103,
        0,
        500
      ],
      [
        10,
        0,
        165,
        [
          219,
          201,
          183,
          165
        ]
      ],
      [
        13,
        7
      ],
      [
        16,
        255,
        1
      ],
      [
        101,
        1,
        136,
        7
      ],
      [
        8,
        0,
        17,
        7
      ],
      [
        6,
        6
      ],
      [
        7,
        1
      ],
      [
        303,
        3
      ],
      [
        303,
        6
      ],
      [
        303,
        9
      ],
      [
        303,
        11
      ],
      [
        10,
        1,
        183,
        [
          237,
          219,
          201,
          183
        ]
      ],
      [
        16,
        165,
        1
      ],
      [
        101,
        0,
        290,
        15
      ],
      [
        103,
        1,
        58
      ],
      [
        301,
        277,
        14,
        1,
        1,
        54,
        8,
        2,
        5
      ],
      [
        16,
        165,
        1
      ],
      [
        101,
        0,
        257,
        13
      ],
      [
        103,
        1,
        51
      ],
      [
        14,
        14,
        8
      ],
      [
        12,
        1,
        183,
        1
      ],
      [
        103,
        1,
        74
      ],
      [
        8,
        1,
        14,
        5
      ],
      [
        7,
        2
      ],
      [
        10,
        2,
        344,
        [
          362,
          344
        ]
      ],
      [
        8,
        2,
        6,
        2
      ],
      [
        7,
        0
      ],
      [
        303,
        12
      ],
      [
        10,
        0,
        129,
        [
          147,
          129
        ]
      ],
      [
        13,
        23
      ],
      [
        16,
        183,
        1
      ],
      [
        101,
        1,
        234,
        12
      ],
      [
        16,
        183,
        1
      ],
      [
        101,
        1,
        236,
        12
      ],
      [
        16,
        183,
        2
      ],
      [
        101,
        1,
        313,
        47
      ],
      [
        8,
        0,
        17,
        7
      ],
      [
        6,
        7
      ],
      [
        7,
        1
      ],
      [
        303,
        13
      ],
      [
        10,
        1,
        147,
        [
          165,
          147
        ]
      ],
      [
        12,
        20,
        147,
        1
      ],
      [
        302,
        22,
        15,
        1,
        1,
        6,
        50,
        4
      ],
      [
        12,
        60,
        147,
        1
      ],
      [
        302,
        96,
        16,
        1,
        1,
        42,
        181,
        3
      ],
      [
        12,
        1,
        147,
        1
      ],
      [
        103,
        1,
        80
      ],
      [
        8,
        1,
        14,
        5
      ],
      [
        7,
        2
      ],
      [
        10,
        2,
        308,
        [
          326,
          308
        ]
      ],
      [
        8,
        2,
        6,
        2
      ],
      [
        7,
        0
      ],
      [
        10,
        0,
        4,
        [
          112,
          94,
          76,
          58,
          40,
          22,
          4
        ]
      ],
      [
        8,
        0,
        17,
        7
      ],
      [
        6,
        8
      ],
      [
        7,
        1
      ],
      [
        303,
        14
      ],
      [
        10,
        1,
        58,
        [
          129,
          112,
          94,
          76,
          58
        ]
      ],
      [
        12,
        18,
        58,
        1
      ],
      [
        302,
        20,
        17,
        1,
        1,
        6,
        76,
        3
      ],
      [
        12,
        4,
        58,
        1
      ],
      [
        103,
        1,
        702
      ],
      [
        13,
        8
      ],
      [
        8,
        1,
        14,
        5
      ],
      [
        7,
        2
      ],
      [
        10,
        2,
        273,
        [
          291,
          273
        ]
      ],
      [
        8,
        2,
        6,
        2
      ],
      [
        7,
        0
      ],
      [
        10,
        0,
        21,
        [
          21
        ]
      ],
      [
        16,
        58,
        2
      ],
      [
        101,
        1,
        310,
        47
      ],
      [
        16,
        58,
        2
      ],
      [
        101,
        1,
        330,
        50
      ],
      [
        16,
        58,
        1
      ],
      [
        101,
        1,
        209,
        10
      ],
      [
        8,
        0,
        17,
        7
      ],
      [
        6,
        9
      ],
      [
        7,
        1
      ],
      [
        10,
        1,
        4,
        [
          40,
          22,
          4
        ]
      ],
      [
        13,
        35
      ],
      [
        12,
        33,
        4,
        1
      ],
      [
        302,
        15,
        18,
        1,
        1,
        32,
        2,
        3
      ],
      [
        16,
        21,
        1
      ],
      [
        101,
        0,
        269,
        13
      ],
      [
        103,
        1,
        54
      ],
      [
        301,
        277,
        19,
        1,
        1,
        54,
        8,
        2,
        5
      ],
      [
        12,
        21,
        4,
        2
      ],
      [
        302,
        23,
        20,
        1,
        1,
        5,
        22,
        2
      ],
      [
        12,
        1,
        4,
        2
      ],
      [
        103,
        1,
        105
      ],
      [
        8,
        1,
        16,
        5
      ],
      [
        7,
        2
      ],
      [
        10,
        2,
        237,
        [
          255,
          237
        ]
      ],
      [
        8,
        2,
        6,
        2
      ],
      [
        7,
        0
      ],
      [
        10,
        0,
        70,
        [
          3,
          20,
          37,
          54,
          71,
          88,
          70
        ]
      ],
      [
        8,
        0,
        17,
        7
      ],
      [
        6,
        10
      ],
      [
        7,
        1
      ],
      [
        303,
        16
      ],
      [
        10,
        1,
        54,
        [
          21,
          3,
          20,
          37,
          54
        ]
      ],
      [
        12,
        24,
        54,
        1
      ],
      [
        302,
        8,
        21,
        1,
        1,
        38,
        89,
        2
      ],
      [
        12,
        5,
        54,
        1
      ],
      [
        302,
        11,
        22,
        1,
        1,
        2,
        122,
        3
      ],
      [
        12,
        2,
        54,
        1
      ],
      [
        103,
        1,
        136
      ],
      [
        12,
        1,
        54,
        1
      ],
      [
        103,
        1,
        82
      ],
      [
        8,
        1,
        16,
        5
      ],
      [
        7,
        2
      ],
      [
        10,
        2,
        201,
        [
          219,
          201
        ]
      ],
      [
        8,
        2,
        6,
        2
      ],
      [
        7,
        0
      ],
      [
        10,
        0,
        195,
        [
          88,
          106,
          124,
          142,
          160,
          178,
          195
        ]
      ],
      [
        8,
        0,
        17,
        7
      ],
      [
        6,
        11
      ],
      [
        7,
        1
      ],
      [
        103,
        1,
        122
      ],
      [
        303,
        15
      ],
      [
        303,
        17
      ],
      [
        303,
        19
      ],
      [
        303,
        20
      ],
      [
        10,
        1,
        143,
        [
          72,
          90,
          108,
          125,
          143
        ]
      ],
      [
        13,
        9
      ],
      [
        12,
        34,
        143,
        1
      ],
      [
        302,
        16,
        23,
        1,
        1,
        32,
        5,
        1
      ],
      [
        12,
        16,
        195,
        1
      ],
      [
        101,
        0,
        126,
        6
      ],
      [
        5,
        0,
        1
      ],
      [
        103,
        1,
        25
      ],
      [
        12,
        1,
        143,
        2
      ],
      [
        103,
        1,
        108
      ],
      [
        12,
        43,
        142,
        1
      ],
      [
        9,
        1,
        3,
        142,
        1
      ],
      [
        8,
        1,
        21,
        5
      ]
    ],
    "dead": {
      "129288": true,
      "91393": false
    },
    "leeks": [
      {
        "agility": 200,
        "cellPos": 367,
        "face": 2,
        "farmer": 86213,
        "frequency": 100,
        "id": 1,
        "level": 224,
        "life": 1409,
        "magic": 0,
        "metal": false,
        "mp": 5,
        "name": "WeekyLeak",
        "orientation": -1,
        "resistance": 100,
        "science": 0,
        "skin": 5,
        "strength": 400,
        "summon": false,
        "team": 2,
        "tp": 14,
        "type": 0,
        "wisdom": 200
      },
      {
        "agility": 500,
        "cellPos": 143,
        "face": 0,
        "farmer": 18035,
        "frequency": 120,
        "id": 0,
        "level": 216,
        "life": 2075,
        "magic": 0,
        "metal": false,
        "mp": 7,
        "name": "EbolaLeek",
        "orientation": -1,
        "resistance": -20,
        "science": 60,
        "skin": 24,
        "strength": 500,
        "summon": false,
        "team": 1,
        "tp": 17,
        "type": 0,
        "wisdom": 0
      },
      {
        "agility": 74,
        "cellPos": 366,
        "critical": false,
        "face": 0,
        "farmer": 86213,
        "frequency": 0,
        "id": 2,
        "level": 105,
        "life": 549,
        "magic": 0,
        "metal": false,
        "mp": 2,
        "name": "rocky_bulb",
        "orientation": -1,
        "owner": 1,
        "resistance": 149,
        "science": 0,
        "skin": 4,
        "strength": 149,
        "summon": true,
        "team": 2,
        "tp": 6,
        "type": 1,
        "wisdom": 0
      },
      {
        "agility": 74,
        "cellPos": 142,
        "critical": false,
        "face": 0,
        "farmer": 86213,
        "frequency": 0,
        "id": 3,
        "level": 105,
        "life": 549,
        "magic": 0,
        "metal": false,
        "mp": 2,
        "name": "rocky_bulb",
        "orientation": -1,
        "owner": 1,
        "resistance": 149,
        "science": 0,
        "skin": 4,
        "strength": 149,
        "summon": true,
        "team": 2,
        "tp": 6,
        "type": 1,
        "wisdom": 0
      }
    ],
    "map": {
      "height": 18,
      "obstacles": {
        "0": 1,
        "126": 1,
        "150": 2,
        "152": 1,
        "155": 2,
        "164": 2,
        "18": 2,
        "187": 1,
        "193": 2,
        "194": 1,
        "206": 1,
        "214": 1,
        "240": 1,
        "241": 1,
        "244": 2,
        "252": 2,
        "259": 1,
        "268": 1,
        "280": 1,
        "290": 1,
        "297": 1,
        "300": 1,
        "302": 2,
        "314": 2,
        "325": 1,
        "335": 1,
        "336": 1,
        "346": 2,
        "347": 1,
        "348": 1,
        "354": 2,
        "359": 2,
        "368": 1,
        "374": 1,
        "379": 1,
        "38": 2,
        "393": 1,
        "413": 2,
        "414": 1,
        "422": 2,
        "43": 1,
        "455": 1,
        "458": 1,
        "459": 1,
        "462": 1,
        "465": 1,
        "469": 2,
        "471": 1,
        "482": 1,
        "483": 1,
        "50": 1,
        "501": 1,
        "505": 2,
        "506": 1,
        "507": 1,
        "512": 2,
        "537": 1,
        "538": 2,
        "558": 2,
        "589": 1,
        "590": 1,
        "603": 1,
        "62": 2,
        "69": 2,
        "8": 1,
        "93": 2,
        "96": 1
      },
      "type": 2,
      "width": 18
    },
    "ops": {
      "0": 9686394,
      "1": 643810
    }
  }
}