{
  "id": 49397806,
  "date": 1758649401,
  "year": 2025,
  "type": 0,
  "context": 2,
  "status": 2,
  "winner": 1,
  "leeks1": [
    {
      "id": 129288,
      "name": "EbolaLeek",
      "level": 255,
      "talent": 1000,
      "hat": 0,
      "skin": 24,
      "farmer": 18035,
      "weapon": 0,
      "title": [],
      "metal": 0,
      "face": 0
    }
  ],
  "leeks2": [
    {
      "id": 113047,
      "name": "31CHIPICEBERG",
      "level": 253,
      "talent": 1052,
      "hat": 0,
      "skin": 1,
      "farmer": 104896,
      "weapon": 0,
      "title": [],
      "metal": 0,
      "face": 0
    }
  ],
  "farmers1": {
    "18035": {
      "id": 18035,
      "name": "Virus",
      "avatar_changed": 1756478013,
      "muted": false
    }
  },
  "farmers2": {
    "104896": {
      "id": 104896,
      "name": "CHIPFORTRESS",
      "avatar_changed": 0,
      "muted": false
    }
  },
  "report": {
    "bonus": 1,
    "duration": 8,
    "leeks1": [
      {
        "appearance": 9,
        "cur_xp": 8910716,
        "dead": false,
        "id": 129288,
        "level": 255,
        "money": 2810,
        "name": "EbolaLeek",
        "next_xp": 8944512,
        "prev_xp": 8843471,
        "resources": {},
        "talent": 1032,
        "talent_gain": 16,
        "tb": 156,
        "td": 169,
        "xp": 3767,
        "xp_locked": false
      }
    ],
    "leeks2": [
      {
        "appearance": 9,
        "cur_xp": 8656622,
        "dead": true,
        "id": 113047,
        "level": 253,
        "money": 500,
        "name": "31CHIPICEBERG",
        "next_xp": 8743080,
        "prev_xp": 8643337,
        "resources": {
          "191": 1
        },
        "talent": 1070,
        "talent_gain": -16,
        "tb": 154,
        "td": 162,
        "xp": 611,
        "xp_locked": false
      }
    ],
    "win": 1
  },
  "comments": [],
  "tournament": -1,
  "views": 1,
  "starter": 18035,
  "trophies": [],
  "seed": 1649315105,
  "team1_name": "EbolaLeek",
  "team2_name": "31CHIPICEBERG",
  "data": {
    "actions": [
      [
        0
      ],
      [
        7,
        0
      ],
      [
        12,
        81,
        140,
        1
      ],
      [
        302,
        155,
        0,
        0,
        0,
        44,
        264,
        2
      ],
      [
        12,
        38,
        140,
        1
      ],
      [
        104,
        0,
        117
      ],
      [
        12,
        80,
        140,
        2
      ],
      [
        104,
        0,
        431
      ],
      [
        10,
        0,
        158,
        [
          158
        ]
      ],
      [
        10,
        0,
        175,
        [
          175
        ]
      ],
      [
        10,
        0,
        193,
        [
          193
        ]
      ],
      [
        10,
        0,
        210,
        [
          210
        ]
      ],
      [
        10,
        0,
        228,
        [
          228
        ]
      ],
      [
        10,
        0,
        246,
        [
          246
        ]
      ],
      [
        10,
        0,
        264,
        [
          264
        ]
      ],
      [
        8,
        0,
        20,
        7
      ],
      [
        7,
        1
      ],
      [
        12,
        20,
        48,
        1
      ],
      [
        302,
        22,
        1,
        1,
        1,
        6,
        73,
        4
      ],
      [
        12,
        18,
        48,
        1
      ],
      [
        302,
        20,
        2,
        1,
        1,
        6,
        58,
        3
      ],
      [
        12,
        82,
        48,
        1
      ],
      [
        302,
        156,
        3,
        1,
        1,
        39,
        169,
        2
      ],
      [
        10,
        1,
        30,
        [
          30
        ]
      ],
      [
        10,
        1,
        12,
        [
          12
        ]
      ],
      [
        10,
        1,
        10,
        [
          29,
          11,
          28,
          10
        ]
      ],
      [
        8,
        1,
        19,
        6
      ],
      [
        7,
        2
      ],
      [
        8,
        2,
        20,
        0
      ],
      [
        6,
        2
      ],
      [
        7,
        0
      ],
      [
        12,
        27,
        264,
        1
      ],
      [
        302,
        9,
        4,
        0,
        0,
        41,
        88,
        2
      ],
      [
        10,
        0,
        247,
        [
          247
        ]
      ],
      [
        10,
        0,
        230,
        [
          230
        ]
      ],
      [
        10,
        0,
        213,
        [
          213
        ]
      ],
      [
        10,
        0,
        196,
        [
          196
        ]
      ],
      [
        10,
        0,
        179,
        [
          179
        ]
      ],
      [
        10,
        0,
        162,
        [
          162
        ]
      ],
      [
        10,
        0,
        145,
        [
          145
        ]
      ],
      [
        12,
        9,
        10,
        2
      ],
      [
        101,
        1,
        0,
        0
      ],
      [
        12,
        9,
        10,
        2
      ],
      [
        101,
        1,
        0,
        0
      ],
      [
        12,
        9,
        10,
        1
      ],
      [
        101,
        1,
        0,
        0
      ],
      [
        12,
        9,
        10,
        1
      ],
      [
        101,
        1,
        0,
        0
      ],
      [
        12,
        9,
        10,
        2
      ],
      [
        101,
        1,
        0,
        0
      ],
      [
        8,
        0,
        20,
        7
      ],
      [
        7,
        1
      ],
      [
        12,
        61,
        145,
        1
      ],
      [
        302,
        97,
        5,
        1,
        0,
        13,
        129,
        3,
        1
      ],
      [
        10,
        1,
        27,
        [
          27
        ]
      ],
      [
        10,
        1,
        9,
        [
          9
        ]
      ],
      [
        10,
        1,
        26,
        [
          26
        ]
      ],
      [
        12,
        62,
        145,
        1
      ],
      [
        302,
        98,
        6,
        1,
        0,
        13,
        213,
        3,
        1
      ],
      [
        13,
        8
      ],
      [
        16,
        145,
        1
      ],
      [
        101,
        0,
        60,
        3
      ],
      [
        301,
        46,
        7,
        1,
        0,
        13,
        205,
        2,
        1
      ],
      [
        12,
        9,
        145,
        1
      ],
      [
        101,
        0,
        17,
        1
      ],
      [
        10,
        1,
        44,
        [
          44
        ]
      ],
      [
        10,
        1,
        62,
        [
          62
        ]
      ],
      [
        8,
        1,
        19,
        6
      ],
      [
        7,
        2
      ],
      [
        8,
        2,
        20,
        0
      ],
      [
        6,
        3
      ],
      [
        7,
        0
      ],
      [
        110,
        0,
        129,
        13
      ],
      [
        110,
        0,
        213,
        21
      ],
      [
        110,
        0,
        205,
        21
      ],
      [
        303,
        0
      ],
      [
        10,
        0,
        128,
        [
          128
        ]
      ],
      [
        10,
        0,
        111,
        [
          111
        ]
      ],
      [
        10,
        0,
        94,
        [
          94
        ]
      ],
      [
        10,
        0,
        77,
        [
          77
        ]
      ],
      [
        10,
        0,
        59,
        [
          59
        ]
      ],
      [
        10,
        0,
        41,
        [
          41
        ]
      ],
      [
        12,
        70,
        41,
        1
      ],
      [
        303,
        5
      ],
      [
        303,
        6
      ],
      [
        303,
        7
      ],
      [
        307,
        0
      ],
      [
        103,
        0,
        50
      ],
      [
        13,
        11
      ],
      [
        16,
        62,
        2
      ],
      [
        101,
        1,
        497,
        75
      ],
      [
        103,
        0,
        25
      ],
      [
        16,
        62,
        1
      ],
      [
        101,
        1,
        358,
        18
      ],
      [
        103,
        0,
        18
      ],
      [
        10,
        0,
        23,
        [
          23
        ]
      ],
      [
        8,
        0,
        20,
        7
      ],
      [
        7,
        1
      ],
      [
        303,
        3
      ],
      [
        12,
        70,
        62,
        1
      ],
      [
        307,
        1
      ],
      [
        103,
        1,
        103
      ],
      [
        12,
        94,
        62,
        1
      ],
      [
        302,
        168,
        8,
        1,
        1,
        2,
        172,
        4
      ],
      [
        10,
        1,
        80,
        [
          80
        ]
      ],
      [
        10,
        1,
        98,
        [
          98
        ]
      ],
      [
        10,
        1,
        115,
        [
          115
        ]
      ],
      [
        12,
        61,
        23,
        1
      ],
      [
        302,
        97,
        9,
        1,
        0,
        13,
        98,
        3,
        1
      ],
      [
        12,
        9,
        23,
        1
      ],
      [
        101,
        0,
        13,
        1
      ],
      [
        103,
        1,
        3
      ],
      [
        8,
        1,
        19,
        6
      ],
      [
        7,
        2
      ],
      [
        8,
        2,
        20,
        0
      ],
      [
        6,
        4
      ],
      [
        7,
        0
      ],
      [
        110,
        0,
        98,
        10
      ],
      [
        303,
        4
      ],
      [
        12,
        24,
        23,
        2
      ],
      [
        302,
        8,
        10,
        0,
        0,
        38,
        122,
        2
      ],
      [
        10,
        0,
        41,
        [
          41
        ]
      ],
      [
        10,
        0,
        59,
        [
          59
        ]
      ],
      [
        16,
        115,
        2
      ],
      [
        101,
        1,
        607,
        91
      ],
      [
        103,
        0,
        30
      ],
      [
        16,
        115,
        2
      ],
      [
        101,
        1,
        640,
        96
      ],
      [
        103,
        0,
        32
      ],
      [
        12,
        9,
        115,
        1
      ],
      [
        101,
        1,
        0,
        0
      ],
      [
        10,
        0,
        6,
        [
          41,
          23,
          6
        ]
      ],
      [
        8,
        0,
        20,
        7
      ],
      [
        7,
        1
      ],
      [
        103,
        1,
        172
      ],
      [
        303,
        2
      ],
      [
        12,
        4,
        115,
        2
      ],
      [
        103,
        1,
        1544
      ],
      [
        12,
        9,
        6,
        1
      ],
      [
        101,
        0,
        19,
        1
      ],
      [
        12,
        9,
        6,
        1
      ],
      [
        101,
        0,
        15,
        1
      ],
      [
        10,
        1,
        97,
        [
          97
        ]
      ],
      [
        10,
        1,
        114,
        [
          114
        ]
      ],
      [
        12,
        62,
        23,
        1
      ],
      [
        302,
        98,
        11,
        1,
        0,
        13,
        106,
        3,
        1
      ],
      [
        10,
        1,
        132,
        [
          132
        ]
      ],
      [
        10,
        1,
        149,
        [
          149
        ]
      ],
      [
        10,
        1,
        166,
        [
          166
        ]
      ],
      [
        8,
        1,
        19,
        6
      ],
      [
        7,
        2
      ],
      [
        8,
        2,
        20,
        0
      ],
      [
        6,
        5
      ],
      [
        7,
        0
      ],
      [
        110,
        0,
        98,
        10
      ],
      [
        110,
        0,
        106,
        11
      ],
      [
        12,
        27,
        6,
        1
      ],
      [
        302,
        9,
        12,
        0,
        0,
        41,
        86,
        2
      ],
      [
        10,
        0,
        23,
        [
          23
        ]
      ],
      [
        10,
        0,
        40,
        [
          40
        ]
      ],
      [
        13,
        25
      ],
      [
        10,
        0,
        6,
        [
          23,
          6
        ]
      ],
      [
        12,
        9,
        166,
        2
      ],
      [
        101,
        1,
        40,
        6
      ],
      [
        103,
        0,
        2
      ],
      [
        12,
        9,
        166,
        2
      ],
      [
        101,
        1,
        48,
        7
      ],
      [
        103,
        0,
        2
      ],
      [
        12,
        9,
        166,
        2
      ],
      [
        101,
        1,
        59,
        9
      ],
      [
        103,
        0,
        3
      ],
      [
        12,
        9,
        166,
        1
      ],
      [
        101,
        1,
        23,
        1
      ],
      [
        103,
        0,
        1
      ],
      [
        12,
        9,
        166,
        2
      ],
      [
        101,
        1,
        40,
        6
      ],
      [
        103,
        0,
        2
      ],
      [
        10,
        0,
        59,
        [
          23,
          41,
          59
        ]
      ],
      [
        8,
        0,
        20,
        7
      ],
      [
        7,
        1
      ],
      [
        103,
        1,
        172
      ],
      [
        303,
        1
      ],
      [
        12,
        18,
        166,
        1
      ],
      [
        302,
        20,
        13,
        1,
        1,
        6,
        58,
        3
      ],
      [
        12,
        82,
        166,
        1
      ],
      [
        302,
        156,
        14,
        1,
        1,
        39,
        158,
        2
      ],
      [
        10,
        1,
        149,
        [
          149
        ]
      ],
      [
        10,
        1,
        132,
        [
          132
        ]
      ],
      [
        12,
        61,
        59,
        1
      ],
      [
        302,
        97,
        15,
        1,
        0,
        13,
        132,
        3,
        1
      ],
      [
        12,
        9,
        59,
        1
      ],
      [
        101,
        0,
        16,
        1
      ],
      [
        103,
        1,
        4
      ],
      [
        10,
        1,
        115,
        [
          115
        ]
      ],
      [
        10,
        1,
        98,
        [
          98
        ]
      ],
      [
        8,
        1,
        19,
        6
      ],
      [
        7,
        2
      ],
      [
        8,
        2,
        20,
        0
      ],
      [
        6,
        6
      ],
      [
        7,
        0
      ],
      [
        110,
        0,
        98,
        10
      ],
      [
        110,
        0,
        106,
        11
      ],
      [
        110,
        0,
        132,
        13
      ],
      [
        303,
        10
      ],
      [
        10,
        0,
        42,
        [
          42
        ]
      ],
      [
        10,
        0,
        25,
        [
          25
        ]
      ],
      [
        10,
        0,
        7,
        [
          7
        ]
      ],
      [
        12,
        9,
        98,
        2
      ],
      [
        101,
        1,
        7,
        1
      ],
      [
        13,
        11
      ],
      [
        16,
        98,
        1
      ],
      [
        101,
        1,
        422,
        21
      ],
      [
        103,
        0,
        21
      ],
      [
        16,
        98,
        2
      ],
      [
        101,
        1,
        584,
        88
      ],
      [
        103,
        0,
        29
      ],
      [
        10,
        0,
        41,
        [
          25,
          42,
          59,
          41
        ]
      ],
      [
        8,
        0,
        20,
        7
      ],
      [
        7,
        1
      ],
      [
        103,
        1,
        172
      ],
      [
        303,
        9
      ],
      [
        12,
        61,
        41,
        2
      ],
      [
        302,
        97,
        16,
        1,
        0,
        13,
        157,
        3,
        1
      ],
      [
        10,
        1,
        80,
        [
          80
        ]
      ],
      [
        10,
        1,
        62,
        [
          62
        ]
      ],
      [
        12,
        62,
        41,
        1
      ],
      [
        302,
        98,
        17,
        1,
        0,
        13,
        191,
        3,
        1
      ],
      [
        12,
        9,
        41,
        1
      ],
      [
        101,
        0,
        20,
        1
      ],
      [
        103,
        1,
        4
      ],
      [
        10,
        1,
        80,
        [
          80
        ]
      ],
      [
        12,
        20,
        80,
        1
      ],
      [
        302,
        22,
        18,
        1,
        1,
        6,
        73,
        4
      ],
      [
        10,
        1,
        98,
        [
          98
        ]
      ],
      [
        8,
        1,
        19,
        6
      ],
      [
        7,
        2
      ],
      [
        8,
        2,
        20,
        0
      ],
      [
        6,
        7
      ],
      [
        7,
        0
      ],
      [
        110,
        0,
        106,
        11
      ],
      [
        110,
        0,
        132,
        13
      ],
      [
        110,
        0,
        157,
        31
      ],
      [
        110,
        0,
        191,
        19
      ],
      [
        303,
        12
      ],
      [
        12,
        33,
        41,
        2
      ],
      [
        302,
        15,
        19,
        0,
        0,
        32,
        3,
        3
      ],
      [
        12,
        24,
        41,
        2
      ],
      [
        302,
        8,
        20,
        0,
        0,
        38,
        128,
        2
      ],
      [
        10,
        0,
        59,
        [
          59
        ]
      ],
      [
        10,
        0,
        42,
        [
          42
        ]
      ],
      [
        10,
        0,
        25,
        [
          25
        ]
      ],
      [
        10,
        0,
        7,
        [
          7
        ]
      ],
      [
        12,
        70,
        7,
        1
      ],
      [
        303,
        11
      ],
      [
        303,
        15
      ],
      [
        303,
        16
      ],
      [
        303,
        17
      ],
      [
        307,
        0
      ],
      [
        103,
        0,
        51
      ],
      [
        13,
        7
      ],
      [
        16,
        98,
        2
      ],
      [
        101,
        1,
        467,
        70
      ],
      [
        103,
        0,
        23
      ],
      [
        16,
        98,
        2
      ],
      [
        101,
        1,
        416,
        62
      ],
      [
        103,
        0,
        21
      ],
      [
        10,
        0,
        59,
        [
          25,
          42,
          59
        ]
      ],
      [
        8,
        0,
        23,
        7
      ],
      [
        7,
        1
      ],
      [
        103,
        1,
        172
      ],
      [
        303,
        8
      ],
      [
        303,
        14
      ],
      [
        12,
        61,
        59,
        1
      ],
      [
        302,
        97,
        21,
        1,
        0,
        13,
        89,
        3,
        1
      ],
      [
        12,
        47,
        98,
        1
      ],
      [
        103,
        1,
        219
      ],
      [
        12,
        70,
        98,
        2
      ],
      [
        307,
        1
      ],
      [
        103,
        1,
        131
      ],
      [
        10,
        1,
        115,
        [
          115
        ]
      ],
      [
        10,
        1,
        132,
        [
          132
        ]
      ],
      [
        12,
        17,
        42,
        1
      ],
      [
        101,
        0,
        106,
        5
      ],
      [
        103,
        1,
        23
      ],
      [
        10,
        1,
        115,
        [
          115
        ]
      ],
      [
        10,
        1,
        116,
        [
          98,
          116
        ]
      ],
      [
        8,
        1,
        19,
        6
      ],
      [
        7,
        2
      ],
      [
        8,
        2,
        20,
        0
      ],
      [
        6,
        8
      ],
      [
        7,
        0
      ],
      [
        110,
        0,
        89,
        9
      ],
      [
        12,
        27,
        59,
        1
      ],
      [
        302,
        9,
        22,
        0,
        0,
        41,
        92,
        2
      ],
      [
        10,
        0,
        42,
        [
          42
        ]
      ],
      [
        10,
        0,
        25,
        [
          25
        ]
      ],
      [
        12,
        9,
        116,
        2
      ],
      [
        101,
        1,
        7,
        1
      ],
      [
        13,
        11
      ],
      [
        16,
        116,
        2
      ],
      [
        101,
        1,
        579,
        87
      ],
      [
        103,
        0,
        29
      ],
      [
        16,
        116,
        2
      ],
      [
        101,
        1,
        519,
        78
      ],
      [
        5,
        1,
        0
      ],
      [
        303,
        13
      ],
      [
        303,
        18
      ],
      [
        303,
        21
      ],
      [
        103,
        0,
        26
      ],
      [
        10,
        0,
        7,
        [
          7
        ]
      ],
      [
        8,
        0,
        23,
        7
      ]
    ],
    "dead": {
      "0": false,
      "113047": true,
      "129288": false
    },
    "leeks": [
      {
        "agility": 550,
        "cellPos": 140,
        "face": 0,
        "farmer": 18035,
        "frequency": 130,
        "id": 0,
        "level": 255,
        "life": 2497,
        "magic": 0,
        "metal": false,
        "mp": 7,
        "name": "EbolaLeek",
        "orientation": -1,
        "resistance": -20,
        "science": 60,
        "skin": 24,
        "strength": 520,
        "summon": false,
        "team": 1,
        "tp": 20,
        "type": 0,
        "wisdom": 50
      },
      {
        "agility": 60,
        "cellPos": 48,
        "face": 0,
        "farmer": 104896,
        "frequency": 130,
        "id": 1,
        "level": 253,
        "life": 2594,
        "magic": 415,
        "metal": false,
        "mp": 6,
        "name": "31CHIPICEBERG",
        "orientation": -1,
        "resistance": 190,
        "science": 20,
        "skin": 1,
        "strength": 50,
        "summon": false,
        "team": 2,
        "tp": 19,
        "type": 0,
        "wisdom": 220
      },
      {
        "agility": 200,
        "cellPos": 323,
        "face": 0,
        "farmer": -1,
        "frequency": 100,
        "id": 2,
        "level": 200,
        "life": 5000,
        "magic": 0,
        "metal": false,
        "mp": 0,
        "name": "iron_chest",
        "orientation": -1,
        "resistance": 500,
        "science": 0,
        "skin": 0,
        "strength": 1000,
        "summon": false,
        "team": 3,
        "tp": 20,
        "type": 3,
        "wisdom": 500
      }
    ],
    "map": {
      "height": 18,
      "obstacles": {
        "105": 1,
        "108": 1,
        "113": 2,
        "121": 2,
        "125": 1,
        "126": 1,
        "133": 2,
        "135": 1,
        "16": 2,
        "183": 1,
        "19": 1,
        "2": 1,
        "203": 2,
        "218": 1,
        "24": 1,
        "241": 1,
        "244": 2,
        "253": 2,
        "260": 1,
        "269": 2,
        "305": 1,
        "312": 2,
        "315": 1,
        "339": 1,
        "341": 1,
        "351": 1,
        "356": 2,
        "37": 1,
        "379": 1,
        "380": 1,
        "387": 1,
        "395": 1,
        "407": 2,
        "413": 1,
        "427": 1,
        "429": 1,
        "432": 1,
        "440": 2,
        "46": 2,
        "462": 1,
        "478": 2,
        "489": 1,
        "507": 1,
        "510": 2,
        "517": 2,
        "538": 1,
        "551": 1,
        "559": 2,
        "562": 2,
        "570": 1,
        "571": 1,
        "573": 1,
        "583": 1,
        "589": 1,
        "595": 1,
        "601": 1,
        "605": 1,
        "611": 1
      },
      "type": 3,
      "width": 18
    },
    "ops": {
      "0": 15695381,
      "1": 44731242,
      "2": 224
    }
  }
}