{
  "18035": {
    "1016": [
      [
        0,
        10
      ]
    ],
    "1043": [
      [
        0,
        10
      ]
    ],
    "1070": [
      [
        0,
        10
      ]
    ],
    "1101": [
      [
        0,
        10
      ]
    ],
    "1132": [
      [
        0,
        10
      ]
    ],
    "1159": [
      [
        0,
        10
      ]
    ],
    "116": [
      [
        0,
        10
      ]
    ],
    "1186": [
      [
        0,
        10
      ]
    ],
    "1218": [
      [
        0,
        10
      ]
    ],
    "1244": [
      [
        0,
        10
      ]
    ],
    "1274": [
      [
        0,
        10
      ]
    ],
    "1304": [
      [
        0,
        10
      ]
    ],
    "1334": [
      [
        0,
        10
      ]
    ],
    "1360": [
      [
        0,
        10
      ]
    ],
    "1388": [
      [
        0,
        10
      ]
    ],
    "1418": [
      [
        0,
        10
      ]
    ],
    "144": [
      [
        0,
        10
      ]
    ],
    "1451": [
      [
        0,
        10
      ]
    ],
    "1478": [
      [
        0,
        10
      ]
    ],
    "1503": [
      [
        0,
        10
      ]
    ],
    "1532": [
      [
        0,
        10
      ]
    ],
    "1567": [
      [
        0,
        10
      ]
    ],
    "1594": [
      [
        0,
        10
      ]
    ],
    "1620": [
      [
        0,
        10
      ]
    ],
    "1649": [
      [
        0,
        10
      ]
    ],
    "1679": [
      [
        0,
        10
      ]
    ],
    "170": [
      [
        0,
        10
      ]
    ],
    "1709": [
      [
        0,
        10
      ]
    ],
    "1738": [
      [
        0,
        10
      ]
    ],
    "1764": [
      [
        0,
        10
      ]
    ],
    "1795": [
      [
        0,
        10
      ]
    ],
    "1823": [
      [
        0,
        10
      ]
    ],
    "199": [
      [
        0,
        10
      ]
    ],
    "20": [
      [
        0,
        10
      ]
    ],
    "227": [
      [
        0,
        10
      ]
    ],
    "261": [
      [
        0,
        10
      ]
    ],
    "295": [
      [
        0,
        10
      ]
    ],
    "321": [
      [
        0,
        10
      ]
    ],
    "348": [
      [
        0,
        10
      ]
    ],
    "376": [
      [
        0,
        10
      ]
    ],
    "410": [
      [
        0,
        10
      ]
    ],
    "43": [
      [
        0,
        10
      ]
    ],
    "439": [
      [
        0,
        10
      ]
    ],
    "464": [
      [
        0,
        10
      ]
    ],
    "492": [
      [
        0,
        10
      ]
    ],
    "524": [
      [
        0,
        10
      ]
    ],
    "553": [
      [
        0,
        10
      ]
    ],
    "581": [
      [
        0,
        10
      ]
    ],
    "609": [
      [
        0,
        10
      ]
    ],
    "639": [
      [
        0,
        10
      ]
    ],
    "666": [
      [
        0,
        10
      ]
    ],
    "68": [
      [
        0,
        10
      ]
    ],
    "697": [
      [
        0,
        10
      ]
    ],
    "725": [
      [
        0,
        10
      ]
    ],
    "756": [
      [
        0,
        10
      ]
    ],
    "783": [
      [
        0,
        10
      ]
    ],
    "809": [
      [
        0,
        10
      ]
    ],
    "840": [
      [
        0,
        10
      ]
    ],
    "874": [
      [
        0,
        10
      ]
    ],
    "899": [
      [
        0,
        10
      ]
    ],
    "925": [
      [
        0,
        10
      ]
    ],
    "94": [
      [
        0,
        10
      ]
    ],
    "955": [
      [
        0,
        10
      ]
    ],
    "988": [
      [
        0,
        10
      ]
    ]
  }
}